playlist_sync/__init__.py
playlist_sync/__main__.py
playlist_sync/config.py
playlist_sync/deemix_config.py
playlist_sync/playlist.py
playlist_sync-0.1.0.dist-info/LICENSE
playlist_sync-0.1.0.dist-info/METADATA
playlist_sync-0.1.0.dist-info/WHEEL
playlist_sync-0.1.0.dist-info/entry_points.txt
playlist_sync-0.1.0.dist-info/top_level.txt
playlist_sync-0.1.0.dist-info/RECORD
