Metadata-Version: 2.1
Name: playlist-sync
Version: 0.1.0
Summary: A little command line tool to download and sync playlists from Deezer or Spotify to predefined folders.
Home-page: https://github.com/lilianmallardeau/playlist-sync
Author: Lilian Mallardeau
Author-email: lilianmallardeau@gmail.com
License: UNKNOWN
Project-URL: Bug Tracker, https://github.com/lilianmallardeau/playlist-sync/issues
Platform: UNKNOWN
Classifier: Programming Language :: Python :: 3
Classifier: License :: OSI Approved :: GNU General Public License v3 (GPLv3)
Classifier: Operating System :: OS Independent
Requires-Python: >=3.8
License-File: LICENSE
Requires-Dist: click (==8.0.4)
Requires-Dist: deemix (==3.6.6)
Requires-Dist: spotipy (==2.19.0)
